README.txt
setup.py
collective/__init__.py
collective.relatedof.egg-info/PKG-INFO
collective.relatedof.egg-info/SOURCES.txt
collective.relatedof.egg-info/dependency_links.txt
collective.relatedof.egg-info/entry_points.txt
collective.relatedof.egg-info/namespace_packages.txt
collective.relatedof.egg-info/not-zip-safe
collective.relatedof.egg-info/requires.txt
collective.relatedof.egg-info/top_level.txt
collective/relatedof/__init__.py
collective/relatedof/configure.zcml
collective/relatedof/i18n.sh
collective/relatedof/locales/collective.relatedof.pot
collective/relatedof/locales/it/LC_MESSAGES/collective.relatedof.po
collective/relatedof/profiles/default/metadata.xml
collective/relatedof/profiles/default/viewlets.xml
collective/relatedof/viewlets/__init__.py
collective/relatedof/viewlets/configure.zcml
collective/relatedof/viewlets/related_of.pt
collective/relatedof/viewlets/related_of.py
docs/HISTORY.txt