Metadata-Version: 1.0
Name: collective.relatedof
Version: 1.1
Summary: viewlet that shows the objects that relate the current one
Home-page: UNKNOWN
Author: RedTurtle Technology
Author-email: sviluppoplone@redturtle.it
License: GPL
Platform: UNKNOWN
Classifier: Programming Language :: Python
Classifier: Topic :: Software Development :: Libraries :: Python Modules
